astgen/__init__.py
astgen/astgen.py
astgen/layouts.py
astgen/platforms.py
astgen/types.py
astgen/utils.py
astgen/version.py
astgen/__pycache__/__init__.cpython-36.pyc
astgen/__pycache__/version.cpython-36.pyc
astgen/templates/cpp_common
astgen/templates/cpp_enums
astgen/templates/cpp_fwddefs
astgen/templates/cpp_header
astgen/templates/cpp_impl
astgen/templates/cpp_node_header
astgen/templates/cpp_node_impl
astgen/templates/cpp_public
astgen/templates/java_common
astgen/templates/java_onefile
astgen-0.1.6.13.data/scripts/astgen
astgen-0.1.6.13.dist-info/METADATA
astgen-0.1.6.13.dist-info/RECORD
astgen-0.1.6.13.dist-info/WHEEL
astgen-0.1.6.13.dist-info/top_level.txt
