Metadata-Version: 1.1
Name: astgen
Version: 0.1.6.13
Summary: A generator for Abstract Syntax Trees.
Home-page: http://github.com/panyam/astgen/
Author: Sri Panyam
Author-email: sri.panyam@gmail.com
License: UNKNOWN
Platform: UNKNOWN
Classifier: Intended Audience :: Developers
Classifier: License :: OSI Approved :: MIT License
Classifier: Operating System :: OS Independent
Classifier: Topic :: Software Development :: Code Generators
Classifier: Topic :: Software Development :: Compilers
